nonebot_plugin_ehentai_search/__init__.py
nonebot_plugin_ehentai_search/config.py
nonebot_plugin_ehentai_search/metadata.py
nonebot_plugin_ehentai_search-0.1.4.dist-info/LICENSE
nonebot_plugin_ehentai_search-0.1.4.dist-info/METADATA
nonebot_plugin_ehentai_search-0.1.4.dist-info/WHEEL
nonebot_plugin_ehentai_search-0.1.4.dist-info/RECORD
