Metadata-Version: 2.1
Name: nonebot-plugin-ehentai-search
Version: 0.1.4
Summary: ehentai search plugin for NoneBot2
Home-page: https://github.com/N791/nonebot-plugin-ehentai-search
License: MIT
Author: N791
Requires-Python: >=3.8,<4.0
Classifier: License :: OSI Approved :: MIT License
Classifier: Programming Language :: Python :: 3
Classifier: Programming Language :: Python :: 3.8
Classifier: Programming Language :: Python :: 3.9
Classifier: Programming Language :: Python :: 3.10
Classifier: Programming Language :: Python :: 3.11
Classifier: Programming Language :: Python :: 3.12
Requires-Dist: Pillow (>=9.4.0,<10.0.0)
Requires-Dist: beautifulsoup4 (>=4.11.2,<5.0.0)
Requires-Dist: httpx (>=0.23.0,<0.24.0)
Requires-Dist: nonebot-adapter-onebot (>=2.4.4,<3.0.0)
Requires-Dist: nonebot2 (>=2.2.0)
Requires-Dist: playwright (>=1.28.1,<2.0.0)
Project-URL: Documentation, https://github.com/N791/nonebot-plugin-ehentai-search/blob/main/README.md
Project-URL: Repository, https://github.com/N791/nonebot-plugin-ehentai-search
